{
  "$schema": "rusty.manifold.stream.manifest.v1",
  "stream_id": "stream.hand.rig_capture",
  "source_module_id": "module.hand_motion.provider",
  "semantic_family": "hand.rig_capture",
  "sample_schema": "rusty.matter.hand.rig_capture.v1",
  "rate_class": "event",
  "timestamp_domains": [
    "clock.host_monotonic"
  ],
  "retention": {
    "policy": "session"
  },
  "sensitivity": "sensitive",
  "transport_offers": [],
  "subscription": {
    "ui_subscribable": true,
    "max_subscribers": 4
  }
}
